gitcomposer/__init__.py
gitcomposer/main.py
gitcomposer-0.1.1.dist-info/licenses/LICENSE
gitcomposer-0.1.1.dist-info/METADATA
gitcomposer-0.1.1.dist-info/WHEEL
gitcomposer-0.1.1.dist-info/entry_points.txt
gitcomposer-0.1.1.dist-info/top_level.txt
gitcomposer-0.1.1.dist-info/RECORD
