Metadata-Version: 2.4
Name: gitcomposer
Version: 0.1.1
Summary: An AI-powered CLI to generate git commit messages using Google Gemini.
Author-email: Tanmay Choudhary <tanmay.d.choudhary@gmail.com>
License: MIT License
Project-URL: Homepage, https://github.com/Tanmay-R-Choudhary/Git-Commit-Message-Composer
Classifier: License :: OSI Approved :: MIT License
Classifier: Programming Language :: Python :: 3
Classifier: Operating System :: OS Independent
Classifier: Environment :: Console
Classifier: Topic :: Software Development :: Version Control :: Git
Classifier: Topic :: Text Processing :: General
Requires-Python: >=3.8
License-File: LICENSE
Requires-Dist: click>=8.0
Dynamic: license-file
